trp/__init__.py
trp/t_pipeline.py
trp/t_tables.py
trp/trp2.py
trp/trp2_analyzeid.py
trp/trp2_expense.py
trp/trp2_lending.py
streamline_trp-0.1.5.dist-info/METADATA
streamline_trp-0.1.5.dist-info/WHEEL
streamline_trp-0.1.5.dist-info/RECORD
