Metadata-Version: 2.1
Name: streamline-trp
Version: 0.1.5
Summary: 
Author: Doug Qian
Author-email: douglas@spirals.so
Requires-Python: >=3.8,<4.0
Classifier: Programming Language :: Python :: 3
Classifier: Programming Language :: Python :: 3.8
Classifier: Programming Language :: Python :: 3.9
Classifier: Programming Language :: Python :: 3.10
Classifier: Programming Language :: Python :: 3.11
Requires-Dist: logging (>=0.4.9.6,<0.5.0.0)
Requires-Dist: marshmallow (>=3.19.0,<4.0.0)
